{
  "Afghanistan": "Afghanistan",
  "Albania": "Albania",
  "Algeria": "Algeria",
  "American Samoa": "American Samoa",
  "Andorra": "Andorra",
  "Antigua and Barbuda": "Antigua and Barbuda",
  "Argentina": "Argentina",
  "Armenia": "Armenia",
  "Aruba": "Aruba",
  "Australia": "Australia",
  "Austria": "Austria",
  "Azerbaijan": "Azerbaijan",
  "Bahamas": "Bahamas",
  "Bahrain": "Bahrain",
  "Bangladesh": "Bangladesh",
  "Barbados": "Barbados",
  "Belarus": "Belarus",
  "Belgium": "Belgium",
  "Belize": "Belize",
  "Benin": "Benin",
  "Bermuda": "Bermuda",
  "Bhutan": "Bhutan",
  "Bolivia": "Bolivia",
  "Botswana": "Botswana",
  "Brazil": "Brazil",
  "Brunei": "Brunei",
  "Bulgaria": "Bulgaria",
  "Burkina Faso": "Burkina Faso",
  "Cabo Verde": "Cape Verde",
  "Cambodia": "Cambodia",
  "Canada": "Canada",
  "Central African Republic": "Central African Republic",
  "Chile": "Chile",
  "China": "China",
  "Colombia": "Colombia",
  "Costa Rica": "Costa Rica",
  "Croatia": "Croatia",
  "Cuba": "Cuba",
  "Cyprus": "Cyprus",
  "Czechia": "Czechia",
  "Denmark": "Denmark",
  "Djibouti": "Djibouti",
  "Dominica": "Dominica",
  "Dominican Republic": "Dominican Republic",
  "Ecuador": "Ecuador",
  "Egypt": "Egypt",
  "El Salvador": "El Salvador",
  "Estonia": "Estonia",
  "Eswatini": "Eswatini",
  "Fiji": "Fiji",
  "Finland": "Finland",
  "France": "France",
  "French Guiana": "French Guiana",
  "French Polynesia": "French Polynesia",
  "Gabon": "Gabon",
  "Georgia": "Georgia",
  "Germany": "Germany",
  "Greece": "Greece",
  "Greenland": "Greenland",
  "Grenada": "Grenada",
  "Guadeloupe": "Guadeloupe",
  "Guam": "Guam",
  "Guatemala": "Guatemala",
  "Guinea": "Guinea",
  "Guyana": "Guyana",
  "Honduras": "Honduras",
  "Hong Kong": "Hong Kong",
  "Hungary": "Hungary",
  "Iceland": "Iceland",
  "India": "India",
  "Indonesia": "Indonesia",
  "Iran": "Iran",
  "Iraq": "Iraq",
  "Ireland": "Ireland",
  "Israel": "Israel",
  "Italy": "Italy",
  "Ivory Coast": "Cote d'Ivoire",
  "Jamaica": "Jamaica",
  "Japan": "Japan",
  "Jordan": "Jordan",
  "Kazakhstan": "Kazakhstan",
  "Kenya": "Kenya",
  "Kuwait": "Kuwait",
  "Kyrgyzstan": "Kyrgyzstan",
  "Laos": "Laos",
  "Latvia": "Latvia",
  "Lebanon": "Lebanon",
  "Lesotho": "Lesotho",
  "Liberia": "Liberia",
  "Libya": "Libya",
  "Lithuania": "Lithuania",
  "Luxembourg": "Luxembourg",
  "Macao": "Macao",
  "Malaysia": "Malaysia",
  "Maldives": "Maldives",
  "Malta": "Malta",
  "Martinique": "Martinique",
  "Mauritania": "Mauritania",
  "Mauritius": "Mauritius",
  "Mayotte": "Mayotte",
  "Mexico": "Mexico",
  "Moldova": "Moldova",
  "Monaco": "Monaco",
  "Mongolia": "Mongolia",
  "Montenegro": "Montenegro",
  "Morocco": "Morocco",
  "Mozambique": "Mozambique",
  "Myanmar": "Myanmar",
  "Namibia": "Namibia",
  "Nauru": "Nauru",
  "Nepal": "Nepal",
  "Netherlands": "Netherlands",
  "New Caledonia": "New Caledonia",
  "New Zealand": "New Zealand",
  "Nicaragua": "Nicaragua",
  "Nigeria": "Nigeria",
  "North Macedonia": "North Macedonia",
  "Northern Mariana Islands": "Northern Mariana Islands",
  "Norway": "Norway",
  "Oman": "Oman",
  "Pakistan": "Pakistan",
  "Palau": "Palau",
  "Palestine": "Palestine",
  "Panama": "Panama",
  "Paraguay": "Paraguay",
  "Peru": "Peru",
  "Philippines": "Philippines",
  "Poland": "Poland",
  "Portugal": "Portugal",
  "Puerto Rico": "Puerto Rico",
  "Qatar": "Qatar",
  "Romania": "Romania",
  "Russia": "Russia",
  "Rwanda": "Rwanda",
  "R\u00e9union": "Reunion",
  "Saint Kitts and Nevis": "Saint Kitts and Nevis",
  "Saint Lucia": "Saint Lucia",
  "Saint Vincent and the Grenadines": "Saint Vincent and the Grenadines",
  "Samoa": "Samoa",
  "San Marino": "San Marino",
  "Sao Tome and Principe": "Sao Tome and Principe",
  "Saudi Arabia": "Saudi Arabia",
  "Serbia": "Serbia",
  "Seychelles": "Seychelles",
  "Singapore": "Singapore",
  "Slovakia": "Slovakia",
  "Slovenia": "Slovenia",
  "Solomon Islands": "Solomon Islands",
  "South Africa": "South Africa",
  "South Korea": "South Korea",
  "Spain": "Spain",
  "Sri Lanka": "Sri Lanka",
  "Suriname": "Suriname",
  "Sweden": "Sweden",
  "Switzerland": "Switzerland",
  "Syria": "Syria",
  "Taiwan": "Taiwan",
  "Tajikistan": "Tajikistan",
  "Thailand": "Thailand",
  "Timor-Leste": "East Timor",
  "Togo": "Togo",
  "Tonga": "Tonga",
  "Trinidad and Tobago": "Trinidad and Tobago",
  "Tunisia": "Tunisia",
  "Turkey": "Turkey",
  "Turkmenistan": "Turkmenistan",
  "Uganda": "Uganda",
  "Ukraine": "Ukraine",
  "United Arab Emirates": "United Arab Emirates",
  "United Kingdom": "United Kingdom",
  "United States": "United States",
  "Uruguay": "Uruguay",
  "Uzbekistan": "Uzbekistan",
  "Vanuatu": "Vanuatu",
  "Venezuela": "Venezuela",
  "Vietnam": "Vietnam",
  "Yemen": "Yemen",
  "Zambia": "Zambia",
  "Zimbabwe": "Zimbabwe",
  "Bosnia": "Bosnia and Herzegovina",
  "Curaco": "Curacao",
  "Democractic Republic of the Congo": "Democratic Republic of Congo",
  "US Virgin Islands": "United States Virgin Islands"
}