{
  "Australia": "Australia",
  "Austria": "Austria",
  "Azerbaijan": "Azerbaijan",
  "Belgium": "Belgium",
  "Bulgaria": "Bulgaria",
  "Canada": "Canada",
  "Chinese Taipei": "Taiwan",
  "Croatia": "Croatia",
  "Cyprus": "Cyprus",
  "Czechia": "Czechia",
  "Denmark": "Denmark",
  "Estonia": "Estonia",
  "Finland": "Finland",
  "France": "France",
  "Germany": "Germany",
  "Greece": "Greece",
  "Hungary": "Hungary",
  "Iceland": "Iceland",
  "Ireland": "Ireland",
  "Israel": "Israel",
  "Italy": "Italy",
  "Japan": "Japan",
  "Kazakhstan": "Kazakhstan",
  "Kuwait": "Kuwait",
  "Latvia": "Latvia",
  "Liechtenstein": "Liechtenstein",
  "Lithuania": "Lithuania",
  "Luxembourg": "Luxembourg",
  "Malta": "Malta",
  "Monaco": "Monaco",
  "Netherlands": "Netherlands",
  "New Zealand": "New Zealand",
  "Norway": "Norway",
  "Poland": "Poland",
  "Portugal": "Portugal",
  "Qatar": "Qatar",
  "Romania": "Romania",
  "Russia": "Russia",
  "Saudi Arabia": "Saudi Arabia",
  "Slovak Republic": "Slovakia",
  "Slovenia": "Slovenia",
  "Spain": "Spain",
  "Sweden": "Sweden",
  "Switzerland": "Switzerland",
  "Thailand": "Thailand",
  "Timor-Leste": "East Timor",
  "United Arab Emirates": "United Arab Emirates",
  "United Kingdom": "United Kingdom",
  "United States": "United States",
  "Adaptation Fund": "Adaptation Fund",
  "African Development Bank": "African Development Bank",
  "African Development Fund": "African Development Fund",
  "Arab Bank for Economic Development in Africa": "Arab Bank for Economic Development in Africa",
  "Arab Fund (AFESD)": "Arab Fund",
  "Asian Development Bank": "Asian Development Bank",
  "Asian Forest Cooperation Organisation": "Asian Forest Cooperation Organization",
  "Asian Infrastructure Investment Bank": "Asian Infrastructure Investment Bank",
  "CGIAR": "CGIAR",
  "COVID-19 Response and Recovery Multi-Partner Trust Fund": "UN COVID-19 Multi-Partner Trust Fund",
  "Caribbean Development Bank": "Caribbean Development Bank",
  "Center of Excellence in Finance": "Center of Excellence in Finance",
  "Central American Bank for Economic Integration": "Central American Bank for Economic Integration",
  "Central Emergency Response Fund": "Central Emergency Response Fund",
  "Climate Investment Funds": "Climate Investment Funds",
  "Council of Europe Development Bank": "Council of Europe Development Bank",
  "Development Bank of Latin America": "Development Bank of Latin America",
  "EU Institutions": "EU institutions (OECD)",
  "Food and Agriculture Organisation": "Food and Agriculture Organization (FAO)",
  "Global Alliance for Vaccines and Immunization": "Global Alliance for Vaccines and Immunization",
  "Global Environment Facility": "Global Environment Facility",
  "Global Fund": "Global Fund",
  "Global Green Growth Institute": "Global Green Growth Institute",
  "Green Climate Fund": "Green Climate Fund",
  "IFAD": "IFAD",
  "IMF (Concessional Trust Funds)": "IMF (Concessional Trust Funds)",
  "Inter-American Development Bank": "Inter-American Development Bank",
  "International Atomic Energy Agency": "International Atomic Energy Agency",
  "International Bank for Reconstruction and Development": "International Bank for Reconstruction and Development",
  "International Centre for Genetic Engineering and Biotechnology": "International Centre for Genetic Engineering and Biotechnology",
  "International Commission on Missing Persons": "International Commission on Missing Persons",
  "International Development Association": "International Development Association",
  "International Labour Organisation": "International Labour Organization (ILO)",
  "Islamic Development Bank": "Islamic Development Bank",
  "Joint Sustainable Development Goals Fund": "Joint Sustainable Development Goals Fund",
  "Korea": "South Korea",
  "Montreal Protocol": "Montreal Protocol",
  "Nordic Development Fund": "Nordic Development Fund",
  "North American Development Bank": "North American Development Bank",
  "OPEC Fund for International Development": "OPEC Fund for International Development",
  "OSCE": "OSCE",
  "T\u00fcrkiye": "Turkey",
  "UN Capital Development Fund": "UN Capital Development Fund",
  "UN Development Coordination Office": "UN Development Coordination Office",
  "UN Institute for Disarmament Research": "UN Institute for Disarmament Research",
  "UN Peacebuilding Fund": "UN Peacebuilding Fund",
  "UN Women": "UN Women",
  "UNAIDS": "UNAIDS",
  "UNDP": "UNDP",
  "UNECE": "UNECE",
  "UNEP": "UNEP",
  "UNFPA": "UNFPA",
  "UNHCR": "UNHCR",
  "UNICEF": "UNICEF",
  "UNRWA": "UNRWA",
  "United Nations Conference on Trade and Development": "United Nations Conference on Trade and Development (UNCTAD)",
  "United Nations Industrial Development Organization": "United Nations Industrial Development Organization (UNIDO)",
  "WFP": "WFP",
  "WHO-Strategic Preparedness and Response Plan": "WHO Strategic Preparedness and Response Plan",
  "WTO - International Trade Centre": "WTO - International Trade Centre",
  "World Health Organisation": "World Health Organization (WHO)",
  "World Organisation for Animal Health": "World Organization for Animal Health",
  "World Tourism Organisation": "World Tourism Organization (UNWTO)",
  "World Trade Organisation": "World Trade Organization (WTO)",
  "all_bilateral": "All bilateral donors (ONE)",
  "all_official": "Official donors (OECD)",
  "dac_members": "DAC countries (OECD)",
  "eu27_countries": "European Union (27)",
  "eu27_total": "European Union (27) + EU institutions",
  "g7": "G7 countries (OECD)",
  "multilateral": "Multilateral organizations (OECD)",
  "non_dac_countries": "Non-DAC countries (OECD)"
}