{
  "Argentina": "Argentina",
  "Belgium": "Belgium",
  "Brazil": "Brazil",
  "Bulgaria": "Bulgaria",
  "Burma": "Myanmar",
  "Canada": "Canada",
  "Chile": "Chile",
  "Colombia": "Colombia",
  "Cuba": "Cuba",
  "Egypt": "Egypt",
  "Finland": "Finland",
  "France": "France",
  "Greece": "Greece",
  "Honduras": "Honduras",
  "Hungary": "Hungary",
  "India": "India",
  "Italy": "Italy",
  "Mexico": "Mexico",
  "Philippines": "Philippines",
  "Portugal": "Portugal",
  "Spain": "Spain",
  "Turkey": "Turkey",
  "United States": "United States",
  "Yugoslavia": "Yugoslavia",
  "Ceylon": "Sri Lanka",
  "nited States": "United States"
}