{
  "Albania": "Albania",
  "Algeria": "Algeria",
  "Argentina": "Argentina",
  "Armenia": "Armenia",
  "Australia": "Australia",
  "Azerbaijan": "Azerbaijan",
  "Belarus": "Belarus",
  "Belgium": "Belgium",
  "Benin": "Benin",
  "Bolivia": "Bolivia",
  "Botswana": "Botswana",
  "Brazil": "Brazil",
  "Bulgaria": "Bulgaria",
  "Burkina Faso": "Burkina Faso",
  "Burundi": "Burundi",
  "Cambodia": "Cambodia",
  "Cameroon": "Cameroon",
  "Cape Verde": "Cape Verde",
  "Chile": "Chile",
  "China": "China",
  "Colombia": "Colombia",
  "Costa Rica": "Costa Rica",
  "Cote d'Ivoire": "Cote d'Ivoire",
  "Croatia": "Croatia",
  "Cyprus": "Cyprus",
  "Czech Rep.": "Czechia",
  "Dominican Republic": "Dominican Republic",
  "Ecuador": "Ecuador",
  "Egypt": "Egypt",
  "El Salvador": "El Salvador",
  "Estonia": "Estonia",
  "France": "France",
  "Gabon": "Gabon",
  "Georgia": "Georgia",
  "Germany": "Germany",
  "Ghana": "Ghana",
  "Greece": "Greece",
  "Greenland": "Greenland",
  "Guatemala": "Guatemala",
  "Guinea": "Guinea",
  "Honduras": "Honduras",
  "Hong Kong": "Hong Kong",
  "Hungary": "Hungary",
  "India": "India",
  "Indonesia": "Indonesia",
  "Italy": "Italy",
  "Jamaica": "Jamaica",
  "Japan": "Japan",
  "Jordan": "Jordan",
  "Kazakhstan": "Kazakhstan",
  "Kenya": "Kenya",
  "Kosovo": "Kosovo",
  "Latvia": "Latvia",
  "Lebanon": "Lebanon",
  "Lesotho": "Lesotho",
  "Liberia": "Liberia",
  "Lithuania": "Lithuania",
  "Madagascar": "Madagascar",
  "Malawi": "Malawi",
  "Malaysia": "Malaysia",
  "Mali": "Mali",
  "Mauritius": "Mauritius",
  "Mexico": "Mexico",
  "Moldova": "Moldova",
  "Mongolia": "Mongolia",
  "Montenegro": "Montenegro",
  "Morocco": "Morocco",
  "Mozambique": "Mozambique",
  "Myanmar": "Myanmar",
  "Namibia": "Namibia",
  "Netherlands": "Netherlands",
  "Nicaragua": "Nicaragua",
  "Niger": "Niger",
  "Nigeria": "Nigeria",
  "Pakistan": "Pakistan",
  "Palestine": "Palestine",
  "Panama": "Panama",
  "Paraguay": "Paraguay",
  "Peru": "Peru",
  "Poland": "Poland",
  "Portugal": "Portugal",
  "Romania": "Romania",
  "Russia": "Russia",
  "Sao Tome and Principe": "Sao Tome and Principe",
  "Senegal": "Senegal",
  "Serbia": "Serbia",
  "Sierra Leone": "Sierra Leone",
  "Slovenia": "Slovenia",
  "South Africa": "South Africa",
  "Spain": "Spain",
  "Sri Lanka": "Sri Lanka",
  "Sudan": "Sudan",
  "Swaziland": "Eswatini",
  "Sweden": "Sweden",
  "Switzerland": "Switzerland",
  "Taiwan": "Taiwan",
  "Tajikistan": "Tajikistan",
  "Tanzania": "Tanzania",
  "Thailand": "Thailand",
  "Togo": "Togo",
  "Trinidad and Tobago": "Trinidad and Tobago",
  "Tunisia": "Tunisia",
  "Turkey": "Turkey",
  "UK": "United Kingdom",
  "USA": "United States",
  "Uganda": "Uganda",
  "Ukraine": "Ukraine",
  "Uruguay": "Uruguay",
  "Venezuela": "Venezuela",
  "Vietnam": "Vietnam",
  "Yemen": "Yemen",
  "Zambia": "Zambia",
  "Zimbabwe": "Zimbabwe",
  "Bosnia and Herz.": "Bosnia and Herzegovina",
  "FYR Macedonia": "North Macedonia",
  "Korea": "South Korea",
  "Kyrgyz Rep.": "Kyrgyzstan",
  "Slovak Rep.": "Slovakia",
  "Dominican Republic*":"Dominican Republic",
  "Uzbekistan": "Uzbekistan",
  "Malaysia*":"Malaysia"
}